COPYING.txt
PKG-INFO
README.md
README.rst
setup.cfg
setup.py
dist/scanyuan-0.0.3.tar.gz
dist/scanyuan-0.0.4.tar.gz
dist/scanyuan-0.0.5.tar.gz
dist/scanyuan-0.0.6.tar.gz
scanyuan/__init__.py
scanyuan.egg-info/PKG-INFO
scanyuan.egg-info/SOURCES.txt
scanyuan.egg-info/dependency_links.txt
scanyuan.egg-info/requires.txt
scanyuan.egg-info/top_level.txt
scanyuan/__pycache__/__init__.cpython-36.pyc
scanyuan/plotting/scanyuan.py