Metadata-Version: 2.1
Name: scanyuan
Version: 0.0.7
Summary: modified scanpy functions to plot AnnData
Home-page: https://github.com/seqyuan/scanyuan
Author: seqyuan
Author-email: seqyuan@gmail.com
License: MIT
Download-URL: https://codeload.github.com/seqyuan/scanyuan/zip/master
Platform: UNKNOWN
Provides-Extra: anndata
Provides-Extra: seaborn
Provides-Extra: pandas
